fnclogger/__init__.py
fnclogger/logger.py
fnclogger-1.0.7.dist-info/licenses/LICENSE
fnclogger-1.0.7.dist-info/METADATA
fnclogger-1.0.7.dist-info/WHEEL
fnclogger-1.0.7.dist-info/top_level.txt
fnclogger-1.0.7.dist-info/RECORD
